teimc/__init__.py
teimc-1.0.1.dist-info/LICENSE
teimc-1.0.1.dist-info/METADATA
teimc-1.0.1.dist-info/WHEEL
teimc-1.0.1.dist-info/top_level.txt
teimc-1.0.1.dist-info/RECORD
