Metadata-Version: 2.1
Name: teimc
Version: 1.0.1
Summary: Functions for processing imaging mass cytometry data with    tellurium isotopes
Home-page: https://github.com/jaybassan/teimc
Author: Jay Bassan
Author-email: jay.s.bassan@gmail.com
License: UNKNOWN
Keywords: imaging mass cytometry tellurium imc
Platform: UNKNOWN
Classifier: Programming Language :: Python :: 3
Classifier: License :: OSI Approved :: MIT License
Classifier: Operating System :: OS Independent
